application/filemodel_func.py
application/main.py
application/model_view_controller.py
application/predefined_messages.py
application/screen_layout.py
application/classes/coin_cls.py
application/classes/config_cls.py
application/classes/exchange_base_cls.py
application/classes/exchange_classes.py
cryptoasset_data_downloader-1.0.9.dist-info/LICENSE
cryptoasset_data_downloader-1.0.9.dist-info/METADATA
cryptoasset_data_downloader-1.0.9.dist-info/WHEEL
cryptoasset_data_downloader-1.0.9.dist-info/entry_points.txt
cryptoasset_data_downloader-1.0.9.dist-info/top_level.txt
cryptoasset_data_downloader-1.0.9.dist-info/RECORD
