Metadata-Version: 2.1
Name: cryptoasset-data-downloader
Version: 1.0.9
Summary: A desktop application to download historical data of desired crypto assets by connecting several different crypto-exchanges' API
Home-page: https://github.com/serhatci/cryptocurrency-historical-data-downloader
Author: Serhat
Author-email: start.a.huge.foolish.project@gmail.com
License: UNKNOWN
Platform: UNKNOWN
Classifier: Programming Language :: Python :: 3
Classifier: License :: OSI Approved :: MIT License
Classifier: Operating System :: OS Independent
Requires-Python: >=3.6
Requires-Dist: pandas
Requires-Dist: arrow
Requires-Dist: requests
Requires-Dist: PySimpleGUI
